README.md
setup.py
tumblr_dl/__init__.py
tumblr_dl.egg-info/PKG-INFO
tumblr_dl.egg-info/SOURCES.txt
tumblr_dl.egg-info/dependency_links.txt
tumblr_dl.egg-info/entry_points.txt
tumblr_dl.egg-info/not-zip-safe
tumblr_dl.egg-info/requires.txt
tumblr_dl.egg-info/top_level.txt