Metadata-Version: 1.0
Name: tumblr-dl
Version: 2018.12.5.1548
Summary: download media of Tumblr subdomains
Home-page: https://github.com/wdbm/tumblr_dl
Author: Will Breaden Madden
Author-email: wbm@protonmail.ch
License: GPLv3
Platform: UNKNOWN
